pyfotmob/__init__.py
pyfotmob/team.py
pyfotmob-0.0.3.dist-info/LICENSE
pyfotmob-0.0.3.dist-info/METADATA
pyfotmob-0.0.3.dist-info/WHEEL
pyfotmob-0.0.3.dist-info/top_level.txt
pyfotmob-0.0.3.dist-info/RECORD
