Metadata-Version: 2.1
Name: pyfotmob
Version: 0.0.3
Summary: A Python library for interacting with the FotMob API
Home-page: https://github.com/Yoo-Joo/PyFotMob
Author: Youssef Ermili
Author-email: youssef.ermili@gmail.com
License: MIT
Classifier: Programming Language :: Python :: 3
Classifier: License :: OSI Approved :: GNU General Public License v3 (GPLv3)
Classifier: Operating System :: OS Independent
Requires-Python: >=3.5
License-File: LICENSE
Requires-Dist: requests ==2.31.0
Requires-Dist: pydantic ==1.10.8
Requires-Dist: python-benedict ==0.32.0
